MANIFEST.in
README.md
setup.py
pypackager/__init__.py
pypackager/ppkg_arfile.py
pypackager/ppkg_changesfile.py
pypackager/ppkg_constants.py
pypackager/ppkg_debfile.py
pypackager/ppkg_digsigsums.py
pypackager/ppkg_dscfile.py
pypackager/ppkg_md5hash.py
pypackager/ppkg_specfile.py
pypackager/ppkg_tarfile.py
pypackager.egg-info/PKG-INFO
pypackager.egg-info/SOURCES.txt
pypackager.egg-info/dependency_links.txt
pypackager.egg-info/top_level.txt