Metadata-Version: 1.1
Name: pypackager
Version: 4.0.1
Summary: PyPackager is an onboard developpers toolswhich is usefull to create sources and binaryMaemo/Harmattan/MeeGo package.
Home-page: http://khertan.net/pypackager
Author: Benoit HERVIER
Author-email: khertan@khertan.net
License: GPL
Keywords: package debian maemo
Platform: UNKNOWN
Classifier: Development Status :: 5 - Production/Stable
Classifier: Topic :: Software Development :: Build Tools
Classifier: License :: OSI Approved :: GNU General Public License (GPL)
Classifier: Programming Language :: Python
Classifier: Operating System :: POSIX :: Linux
Classifier: Intended Audience :: Developers
